thomas/server/__build__
thomas/server/__init__.py
thomas/server/_version.py
thomas/server/cli.py
thomas/server/ctx.py
thomas/server/error.py
thomas/server/fixtures.py
thomas/server/server.py
thomas/server/data/config.yaml
thomas/server/db/__init__.py
thomas/server/db/network.py
thomas/server/db/security.py
thomas/server/resource/__init__.py
thomas/server/resource/_schema.py
thomas/server/resource/network.py
thomas/server/resource/role.py
thomas/server/resource/session.py
thomas/server/resource/smartonfhir.py
thomas/server/resource/token.py
thomas/server/resource/user.py
thomas/server/resource/version.py
thomas/server/static/.DS_Store
thomas/server/static/asset-manifest.json
thomas/server/static/favicon.ico
thomas/server/static/index.html
thomas/server/static/manifest.json
thomas/server/static/precache-manifest.cc0a9f704d7fb6019afeacbb3ee67148.js
thomas/server/static/service-worker.js
thomas/server/static/static/css/main.94dad45e.chunk.css
thomas/server/static/static/css/main.94dad45e.chunk.css.map
thomas/server/static/static/js/2.e338c557.chunk.js
thomas/server/static/static/js/2.e338c557.chunk.js.LICENSE.txt
thomas/server/static/static/js/2.e338c557.chunk.js.map
thomas/server/static/static/js/main.d123dd5d.chunk.js
thomas/server/static/static/js/main.d123dd5d.chunk.js.map
thomas/server/static/static/js/runtime-main.42c476ce.js
thomas/server/static/static/js/runtime-main.42c476ce.js.map
thomas/server/util/Colorer.py
thomas/server/util/__init__.py
thomas_server-0.1.1a17.dist-info/LICENSE
thomas_server-0.1.1a17.dist-info/METADATA
thomas_server-0.1.1a17.dist-info/WHEEL
thomas_server-0.1.1a17.dist-info/entry_points.txt
thomas_server-0.1.1a17.dist-info/top_level.txt
thomas_server-0.1.1a17.dist-info/RECORD
